Metadata-Version: 2.1
Name: StockPrediction
Version: 1.0
Summary: Use LSTM to predict stock close price
Home-page: https://blog.csdn.net/weixin_43456810
Author: Sherlock Xu
Author-email: sherlockjjobs@icloud.com
License: LGPL
Platform: UNKNOWN
